noah_cli/__init__.py
noah_cli/app/__init__.py
noah_cli/app/main.py
noah_cli/app/state.py
noah_cli/commands/__init__.py
noah_cli/commands/add.py
noah_cli/commands/check.py
noah_cli/commands/fetch.py
noah_cli/commands/info.py
noah_cli/commands/init.py
noah_cli/commands/install.py
noah_cli/commands/offload.py
noah_cli/commands/remove.py
noah_cli/commands/uninstall.py
noah_cli/core/__init__.py
noah_cli/core/config.py
noah_cli/core/console.py
noah_cli/core/file.py
noah_cli/core/network.py
noah_cli/helpers/__init__.py
noah_cli/helpers/app.py
noah_cli/helpers/common.py
noah_cli/helpers/database.py
noah_cli/models/__init__.py
noah_cli/models/app.py
noah_cli/models/config.py
noah_cli/models/container.py
noah_cli/models/data.py
noah_cli/models/workflow.py
noah_cli-0.2.0.dist-info/LICENSE
noah_cli-0.2.0.dist-info/METADATA
noah_cli-0.2.0.dist-info/WHEEL
noah_cli-0.2.0.dist-info/entry_points.txt
noah_cli-0.2.0.dist-info/RECORD
