Metadata-Version: 2.1
Name: noah-cli
Version: 0.2.0
Summary: a project management tool for reproducible, portable, and streamlined bioinformatics analysis
Home-page: https://github.com/raymond-u/noah-cli
Keywords: bioinformatics,project management
Author: raymond-u
Author-email: 36328498+raymond-u@users.noreply.github.com
Requires-Python: >=3.11,<4.0
Classifier: Programming Language :: Python :: 3
Classifier: Programming Language :: Python :: 3.11
Classifier: Topic :: Scientific/Engineering :: Bio-Informatics
Requires-Dist: dacite (>=1.8.1,<2.0.0)
Requires-Dist: fabric (>=3.1.0,<4.0.0)
Requires-Dist: ordered-set (>=4.1.0,<5.0.0)
Requires-Dist: pysradb (>=2.1.0,<3.0.0)
Requires-Dist: requests (>=2.31.0,<3.0.0)
Requires-Dist: ruamel-yaml (>=0.17.32,<0.18.0)
Requires-Dist: typer[all] (>=0.9.0,<0.10.0)
Project-URL: Repository, https://github.com/raymond-u/noah-cli
